picoboot3/__init__.py
picoboot3/cli.py
picoboot3/picoboot3.py
picoboot3/picoboot3_i2c.py
picoboot3/picoboot3_spi.py
picoboot3/picoboot3_uart.py
picoboot3-1.1.0.dist-info/LICENSE
picoboot3-1.1.0.dist-info/METADATA
picoboot3-1.1.0.dist-info/WHEEL
picoboot3-1.1.0.dist-info/entry_points.txt
picoboot3-1.1.0.dist-info/top_level.txt
picoboot3-1.1.0.dist-info/RECORD
